qautomatelibrary/NotifierProviders/O365EmailProvider.py
qautomatelibrary/NotifierProviders/RocketChatProvider.py
qautomatelibrary_notifierproviders-0.1.1.dist-info/METADATA
qautomatelibrary_notifierproviders-0.1.1.dist-info/WHEEL
qautomatelibrary_notifierproviders-0.1.1.dist-info/RECORD
