Metadata-Version: 2.1
Name: qautomatelibrary-notifierproviders
Version: 0.1.1
Summary: Custom providers for Notifiers library
Author: Tony Rintala
Author-email: 72392290+tonyr-qf@users.noreply.github.com
Requires-Python: >=3.9,<4.0
Classifier: Programming Language :: Python :: 3
Classifier: Programming Language :: Python :: 3.9
Classifier: Programming Language :: Python :: 3.10
Classifier: Programming Language :: Python :: 3.11
Classifier: Programming Language :: Python :: 3.12
Requires-Dist: notifiers (==1.3.3)
Requires-Dist: setuptools (>=69.0.3,<70.0.0)
